ergochemics/__init__.py
ergochemics/draw.py
ergochemics/mapping.py
ergochemics/similarity.py
ergochemics/standardize.py
ergochemics-0.1.2.dist-info/licenses/LICENSE.txt
ergochemics-0.1.2.dist-info/METADATA
ergochemics-0.1.2.dist-info/WHEEL
ergochemics-0.1.2.dist-info/top_level.txt
ergochemics-0.1.2.dist-info/RECORD
