Metadata-Version: 2.4
Name: ergochemics
Version: 0.1.2
Summary: Ergonomical cheminformatics library
Author-email: stefanpate <stefanpate94@gmail.com>
License-Expression: MIT
Project-URL: Source Code, https://github.com/stefanpate/ergochemics
Requires-Python: >=3.12
License-File: LICENSE.txt
Requires-Dist: pandas>=2.2.3
Requires-Dist: pydantic>=2.10.6
Requires-Dist: rdkit>=2024.9.5
Dynamic: license-file
